naics_tool/__init__.py
naics_tool/naics_tool.py
naics_tool-0.1.2.dist-info/METADATA
naics_tool-0.1.2.dist-info/WHEEL
naics_tool-0.1.2.dist-info/RECORD
